marketclientpy/__init__.py
marketclientpy/scrappers.py
marketclientpy-0.1.1.dist-info/LICENSE.txt
marketclientpy-0.1.1.dist-info/METADATA
marketclientpy-0.1.1.dist-info/WHEEL
marketclientpy-0.1.1.dist-info/top_level.txt
marketclientpy-0.1.1.dist-info/RECORD
