Metadata-Version: 2.1
Name: marketclientpy
Version: 0.1.1
Summary: Dowload free financial data
Home-page: https://github.com/genarionogueira/marketClient
Author: Genario Nogueira
Author-email: genarionogueira2@gmail.com
License: MIT
Platform: UNKNOWN
Classifier: Programming Language :: Python :: 3
Requires-Dist: pandas
Requires-Dist: datetime
